{
 "path": "1904/02goz04.html",
 "type": "article",
 "title": "御前会議、対露開戦を決定　／ クリック ２０世紀",
 "description": "●世界と日本の近現代史を年表に再現。人物紹介も充実。●年表の2000を超える項目は史実へのインデックスでもある。●歴史は足跡。見つめると人間が、ドラマが、そして未来が見えてくる。  ・・・ Good luck !",
 "css": [
  "../all.css",
  "../b.css",
  "../include/include.css"
 ],
 "baseClass": "base",
 "blocks": [
  {
   "type": "edit_bar",
   "kind": "e_bar",
   "html": "<a name=\"h\"></a>"
  },
  {
   "type": "raw",
   "tag": "div",
   "attrs": {
    "class": "c20"
   },
   "html": "\n<a href=\"../index.html\">－ クリック２０世紀 －</a>"
  },
  {
   "type": "navi",
   "html": "\n<a href=\"../index.html\">目次</a> ＞ <a href=\"../20c/1904.html\">年表</a> ＞ <span class=\"now\">事項</span> ＞ <a href~.html\"=\"\">詳細</a> ／ <a href=\"../p/01a.html\">人物</a> ／ <a href=\"../text/01a.html\">書籍</a> ／ 他"
  },
  {
   "type": "title",
   "html": "御前会議、対露開戦を決定"
  },
  {
   "type": "title2",
   "html": "1904/02/04"
  },
  {
   "type": "navi2",
   "html": "\n１０年前 &gt;&gt;&gt; <a href=\"../20c/1903.html\">前年</a> &gt;&gt;&gt; <a href=\"../20c/1904.html\">１９０４</a> &gt;&gt;&gt; <a href=\"../20c/1905.html\">翌年</a> &gt;&gt;&gt; <a href=\"../20c/1914.html\">１０年後</a>"
  },
  {
   "type": "headline",
   "cells": [
    "日本の首脳たちは、悲壮な決意で大国ロシアとの戦争を決定した。"
   ]
  },
  {
   "type": "raw",
   "tag": "table",
   "attrs": {
    "class": "lt"
   },
   "html": "<tbody><tr><td class=\"lt\"><a href\".html\"=\"\">　</a></td><td class=\"lt\"><a href.html\"=\"\">　</a></td><td class=\"lt\"><a href.html\"=\"\">　</a></td><td class=\"lt\"><a href.html\"=\"\">　</a></td></tr></tbody>"
  },
  {
   "type": "timeline",
   "rows": [
    {
     "cls": "b",
     "cells": [
      {
       "id": "l",
       "cls": null,
       "html": "1903/04/08　　<a href=\"../1903/04teppe.html\">\nロシア、満州撤兵②不履行</a>"
      }
     ]
    },
    {
     "cls": "n",
     "cells": [
      {
       "id": "l",
       "cls": null,
       "html": "1903/04/21　　<a href=\"../1903/04murin.html\">\n無隣庵会議</a>　（<a href=\"../p/yaritomo.html\">山県</a>・<a href=\"../p/ihirobum.html\">伊藤</a>・<a href=\"../p/ktaro.html\">桂</a>・<a href=\"../p/kjutaro.html\">小村</a>／京都）"
      }
     ]
    },
    {
     "cls": "n",
     "cells": [
      {
       "id": "l",
       "cls": null,
       "html": "1903/08/12　　<a href\"..=\"\" 19.html\"=\"\">\nロシア、旅順に極東総督府を設置</a>"
      }
     ]
    },
    {
     "cls": "b",
     "cells": [
      {
       "id": "l",
       "cls": null,
       "html": "1903/10/06　　<a href=\"../1903/10jr_ko.html\">\n日露交渉（小村・ローゼン交渉）開始</a>"
      }
     ]
    },
    {
     "cls": "n",
     "cells": [
      {
       "id": "l",
       "cls": null,
       "html": "1903/12/28　　<a href=\"../1903/12hense.html\">\n連合艦隊編成</a>　（司令長官：<a href=\"../p/theihaci.html\">東郷平八郎</a>）"
      }
     ]
    },
    {
     "cls": "n",
     "cells": [
      {
       "id": "l",
       "cls": null,
       "html": "1903/12/30　　<a href=\"../1903/12kyodo.html\">\n参謀本部・軍令部首脳会議、陸海軍共同作戦計画を決定</a>"
      }
     ]
    },
    {
     "cls": "n",
     "cells": [
      {
       "id": "l",
       "cls": null,
       "html": "1903/12/30　　<a href=\"../1903/12gaiko.html\">\n閣議、対清・対韓政策を決定</a>"
      }
     ]
    },
    {
     "cls": "n",
     "cells": [
      {
       "id": "l",
       "cls": null,
       "html": "1903/12/31　　<a href=\"../1903/12enjyo.html\">\n小村外相、林駐英公使に対英財政援助要請を訓令</a>　（04/01/02 拒否）"
      }
     ]
    },
    {
     "cls": "x",
     "cells": [
      {
       "id": "l",
       "cls": null,
       "html": "1904/02/04　　<a 1904=\"\" href\"..=\"\" 02goz04.html\"=\"\">\n御前会議、対露開戦を決定</a>"
      }
     ]
    },
    {
     "cls": "n",
     "cells": [
      {
       "id": "l",
       "cls": null,
       "html": "1904/02/06　　<a href=\"../1904/02danko.html\">\n栗野駐露公使、ロシアに国交断絶を通告</a>"
      }
     ]
    },
    {
     "cls": "n",
     "cells": [
      {
       "id": "l",
       "cls": null,
       "html": "1904/02/08　　<a href=\"../1904/02jorik.html\">\n陸軍先遣隊、仁川上陸開始</a>"
      }
     ]
    },
    {
     "cls": "n",
     "cells": [
      {
       "id": "l",
       "cls": null,
       "html": "1904/02/09　　<a href=\"../1904/02jinse.html\">\n仁川沖海戦</a>"
      }
     ]
    },
    {
     "cls": "b",
     "cells": [
      {
       "id": "l",
       "cls": null,
       "html": "1904/02/10　　<a href=\"../1904/02jr_wa.html\">\n対露宣戦布告</a>　（<a href=\"../them/jr_war.html\">日露戦争</a>勃発）"
      }
     ]
    }
   ]
  },
  {
   "type": "raw",
   "tag": "div",
   "attrs": {
    "class": "off"
   },
   "html": "\n<div class=\"pt_h\">～　あああ　～</div>\n<div class=\"i1\">あああ</div>\n"
  },
  {
   "type": "raw",
   "tag": "div",
   "attrs": {
    "class": "tx"
   },
   "html": "\n<span class=\"m_v\">taro's トーク</span>\n日露戦争を決意した首脳たちの表情は一様に暗い。\n元老<a href=\"../p/ihirobum.html\">伊藤博文</a>は、もしもロシア軍が九州に上陸してきたら、自分も銃をとって戦う、\n今度の戦争で勝利を期待することは無理だが、全員が命を賭けて最後まで戦えば活路は開けるかもしれないと言った。\n参謀次長<a href=\"../p/kgentaro.html\">児玉源太郎</a>は、せめて六分四分にしたくて泊り込みで作戦を練っているのだと言った。\n海相<a href=\"../p/ygonnohy.html\">山本権兵衛</a>は、日本の軍艦の半分は沈むと言った。\nそれでも彼らは開戦を決意せねばならなかった。\n対米工作を行うため渡米することが決まった<a href=\"../p/kkentaro.html\">金子堅太郎</a>をねぎらうため、皇后はその私邸を訪れている。\n日銀副総裁<a href=\"../p/tkorekiy.html\">高橋是清</a>は、開戦早々軍資金集めの旅に出ている。\n侵略者がいれば、平和主義者が武器をとって戦わねばならぬことはある。\ntaroは日露戦争のときの首脳たちの表情の暗さが好きだ。\n政府に開戦を迫る世論のはしゃぎっぷりは大嫌いだ。\n"
  },
  {
   "type": "raw",
   "tag": "div",
   "attrs": {
    "class": "tx"
   },
   "html": "\n<div><span class=\"m_b\">引用</span>一月二十二日（二月四日）の夕方、東京では、ロシア艦隊が外泊地にいることが明白になった。\n日本の軍司令部は、この好機をつかまえようと決めた。\n日本の最高官吏が出席して開かれた<a href=\"../p/mtenno.html\">天皇</a>の御前会議において、ロシアとの開戦の決定が採択された。\n<a href=\"../p/theihaci.html\">東郷海軍中将</a>は、ロシア艦隊を攻撃し、朝鮮に軍隊を上陸せよとの命令を受けた。\n国内では動員令が発令された。</div>\n<div class=\"txr\"><a href=\"../text/ro_soren.html\">ロストーノフ 「ソ連から見た日露戦争」</a>\n　Ｐ．１１６</div>\n"
  },
  {
   "type": "cyu",
   "html": "※　「クリック２０世紀」では、引用部分を除いて、固有名詞などの表記を極力統一するよう努めています。\n"
  },
  {
   "type": "taro",
   "html": "<a href=\"http://www.c20.jp/\">http://www.c20.jp/</a><br><a href=\"mailto:taro@c20.jp\">おたよりはこちら</a>"
  },
  {
   "type": "raw",
   "tag": "div",
   "attrs": {},
   "html": "\n<script type=\"text/javascript\"><!--\ngoogle_ad_client = \"pub-3232598861909913\";\n/* 468x15, 作成済み 08/10/23 */\ngoogle_ad_slot = \"9077774385\";\ngoogle_ad_width = 468;\ngoogle_ad_height = 15;\n//-->\n</script>\n<script type=\"text/javascript\" src=\"http://pagead2.googlesyndication.com/pagead/show_ads.js\">\n</script>\n"
  },
  {
   "type": "fnavi",
   "html": "\n<a href=\"../index.html\">クリック２０世紀 トップ</a>\n ＞ <a href=\"../20c/1904.html\">１９０４年</a>\n ＞ <a href=\"#h\">御前会議、対露開戦を決定</a>\n　　<span class=\"fmark\"><a href=\"#h\">□◎□</a></span>"
  }
 ]
}