{
 "path": "p/himmle_h.html",
 "type": "person",
 "title": "ハインリッヒ・ヒムラー　／ クリック ２０世紀",
 "description": "●世界と日本の近現代史を年表に再現。人物紹介も充実。●年表の2000を超える項目は史実へのインデックスでもある。●歴史は足跡。見つめると人間が、ドラマが、そして未来が見えてくる。  ・・・ Good luck !",
 "css": [
  "../all.css",
  "p.css"
 ],
 "baseClass": "base",
 "blocks": [
  {
   "type": "edit_bar",
   "kind": "e_bar",
   "html": "<a name=\"h\"></a>"
  },
  {
   "type": "navi",
   "html": "\n<a href=\"../index.html\">目次</a> ＞ 年表 ＞ 事項 ＞ 詳細　／　<span class=\"now\">他</span>　　　<a href=\"javascript:history.back()\"><b>&lt;&lt;&lt;&lt;</b></a>"
  },
  {
   "type": "title",
   "html": "ハインリッヒ・ヒムラー"
  },
  {
   "type": "title2",
   "html": "1900 － 1945"
  },
  {
   "type": "raw",
   "tag": "div",
   "attrs": {
    "class": "prof"
   },
   "html": "\n内相、ゲシュタポ長官、ナチス親衛隊隊長　／ ドイツ"
  },
  {
   "type": "raw",
   "tag": "table",
   "attrs": {
    "class": "lt"
   },
   "html": "<tbody><tr><td class=\"lt\"><a href=\"06h.html\">一覧　（ハ）</a></td><td class=\"lt\"><a href.html\"=\"\">　</a></td><td class=\"lt\"><a href.html\"=\"\">　</a></td><td class=\"lt\"><a href.html\"=\"\">　</a></td></tr></tbody>"
  },
  {
   "type": "raw",
   "tag": "div",
   "attrs": {
    "class": "off"
   },
   "html": "<span class=\"m_r\">エピソード 1</span>調査中。"
  },
  {
   "type": "raw",
   "tag": "div",
   "attrs": {
    "class": "hidden"
   },
   "html": "<a name=\"s1\"></a>\n<a href=\"#s1\">＝</a><a href=\"#h\">△</a><a href=\"#h\">◎</a><a href=\"#s2\">▽</a><a href=\"#s1\">＝</a>"
  },
  {
   "type": "raw",
   "tag": "table",
   "attrs": {
    "class": "off"
   },
   "html": "<tbody><tr><td class=\"hist\">\n・　</td></tr><tr><td class=\"hist\">\n・　</td></tr><tr><td class=\"hist\">\n・　</td></tr><tr><td class=\"hist\">\n・　</td></tr><tr><td class=\"hist\">\n・　</td></tr><tr><td class=\"hist\">\n・　</td></tr><tr><td class=\"hist\">\n・　</td></tr><tr><td class=\"hist\">\n・　</td></tr><tr><td class=\"hist\">\n・　</td></tr></tbody>"
  },
  {
   "type": "raw",
   "tag": "div",
   "attrs": {
    "class": "off"
   },
   "html": "<a name=\"s2\"></a>\n<a href=\"#s2\">＝</a><a href=\"#s1\">△</a><a href=\"#h\">◎</a><a href=\"#s3\">▽</a><a href=\"#s2\">＝</a>"
  },
  {
   "type": "timeline",
   "rows": [
    {
     "cls": "b",
     "cells": [
      {
       "id": "l",
       "cls": null,
       "html": "1932/07/31　　<a href=\"../1932/07nazis.html\">\nナチス、第１党に躍進</a>"
      }
     ]
    },
    {
     "cls": "b",
     "cells": [
      {
       "id": "l",
       "cls": null,
       "html": "1933/01/30　　<a href=\"../1933/01hitle.html\">\nヒトラー内閣成立</a>　（独）"
      }
     ]
    },
    {
     "cls": "n",
     "cells": [
      {
       "id": "l",
       "cls": null,
       "html": "1933/02/27　　<a href=\"../1933/02gijid.html\">\n国会議事堂放火事件</a>　（ベルリン）"
      }
     ]
    },
    {
     "cls": "b",
     "cells": [
      {
       "id": "l",
       "cls": null,
       "html": "1933/03/23　　<a href=\"../1933/03zenke.html\">\nドイツ議会、全権委任法を可決</a>　（ヒトラー独裁体制確立）"
      }
     ]
    },
    {
     "cls": "n",
     "cells": [
      {
       "id": "l",
       "cls": null,
       "html": "1933/04/26　　<a href=\"../1933/04gesch.html\">\nゲジュタポ発足</a>　（長官：<a href=\"../p/goring_h.html\">ゲーリング</a>）"
      }
     ]
    },
    {
     "cls": "n",
     "cells": [
      {
       "id": "l",
       "cls": null,
       "html": "1933/07/14　　<a href=\"../1933/07seito.html\">\nヒトラー、新政党の結成を禁止</a>"
      }
     ]
    },
    {
     "cls": "n",
     "cells": [
      {
       "id": "l",
       "cls": null,
       "html": "1934/06/30　　<a href=\"../1934/06rohmj.html\">\nレーム事件</a>　（<a href=\"../p/hitler_a.html\">ヒトラー</a>、<a href=\"../p/rohm_e.html\">レーム</a>らを粛清）"
      }
     ]
    },
    {
     "cls": "b",
     "cells": [
      {
       "id": "l",
       "cls": null,
       "html": "1935/03/06　　<a href=\"../1935/03d_sai.html\">\nドイツ、再軍備宣言</a>"
      }
     ]
    },
    {
     "cls": "n",
     "cells": [
      {
       "id": "l",
       "cls": null,
       "html": "1935/09/15　　<a href=\"../1935/09nurnb.html\">\nニュルンベルク法公布</a>　（ユダヤ人迫害の法制化）"
      }
     ]
    },
    {
     "cls": "b",
     "cells": [
      {
       "id": "l",
       "cls": null,
       "html": "1935/10/21　　<a href\"..=\"\" 19.html\"=\"\">\nドイツ、国際連盟脱退</a>"
      }
     ]
    },
    {
     "cls": "b",
     "cells": [
      {
       "id": "l",
       "cls": null,
       "html": "1936/03/07　　<a href\"..=\"\" 19.html\"=\"\">\nドイツ軍、ラインラント進駐</a>"
      }
     ]
    },
    {
     "cls": "b",
     "cells": [
      {
       "id": "l",
       "cls": null,
       "html": "1938/03/13　　<a href=\"../1938/03austr.html\">\nドイツ、ドイツ、オーストリア併合</a>"
      }
     ]
    },
    {
     "cls": "n",
     "cells": [
      {
       "id": "l",
       "cls": null,
       "html": "1938/09/29　　<a href=\"../1938/09munch.html\">\nミュンヘン会談</a>"
      }
     ]
    },
    {
     "cls": "b",
     "cells": [
      {
       "id": "l",
       "cls": null,
       "html": "1939/08/23　　<a href=\"../1939/08ds_jy.html\">\n独ソ不可侵条約締結</a>"
      }
     ]
    },
    {
     "cls": "b",
     "cells": [
      {
       "id": "l",
       "cls": null,
       "html": "1939/09/01　　<a href=\"../1939/09taise.html\">\nドイツ軍、ポーランド侵攻開始</a>　（第二次世界大戦勃発）"
      }
     ]
    },
    {
     "cls": "b",
     "cells": [
      {
       "id": "l",
       "cls": null,
       "html": "1940/05/10　　<a href=\"../1940/05seibu.html\">\nドイツ軍、西部戦線に総攻撃開始</a>"
      }
     ]
    },
    {
     "cls": "b",
     "cells": [
      {
       "id": "l",
       "cls": null,
       "html": "1940/06/22　　<a href=\"../1940/06f_kof.html\">\nフランス（ペタン政府）降伏</a>"
      }
     ]
    },
    {
     "cls": "b",
     "cells": [
      {
       "id": "l",
       "cls": null,
       "html": "1940/09/27　　<a href=\"../1940/09jdi_d.html\">\n日独伊三国軍事同盟調印</a>"
      }
     ]
    },
    {
     "cls": "b",
     "cells": [
      {
       "id": "l",
       "cls": null,
       "html": "1941/06/22　　<a href=\"../1941/06ds_ka.html\">\n独ソ戦開始</a>"
      }
     ]
    },
    {
     "cls": "b",
     "cells": [
      {
       "id": "l",
       "cls": null,
       "html": "1943/09/08　　<a href=\"../1943/09i_kof.html\">\nイタリア、無条件降伏</a>"
      }
     ]
    },
    {
     "cls": "n",
     "cells": [
      {
       "id": "l",
       "cls": null,
       "html": "1943/09/12　　<a href=\"../1943/09musso.html\">\nドイツ軍特殊部隊、ムッソリーニ救出</a>"
      }
     ]
    },
    {
     "cls": "b",
     "cells": [
      {
       "id": "l",
       "cls": null,
       "html": "1944/06/06　　<a href=\"../1944/06norma.html\">\n連合軍、ノルマンディー上陸作戦開始</a>　（オーバーロード作戦）"
      }
     ]
    },
    {
     "cls": "b",
     "cells": [
      {
       "id": "l",
       "cls": null,
       "html": "1944/07/20　　<a href=\"../1944/07hitle.html\">\nヒトラー暗殺計画失敗</a>"
      }
     ]
    },
    {
     "cls": "n",
     "cells": [
      {
       "id": "l",
       "cls": null,
       "html": "1945/02/04　　<a href=\"../1945/02yalta.html\">\nヤルタ会談</a>　（～02/11）"
      }
     ]
    },
    {
     "cls": "n",
     "cells": [
      {
       "id": "l",
       "cls": null,
       "html": "1945/04/22　　<a href\"..=\"\" 19.html\"=\"\">\nソ連軍戦車隊、ベルリン市街に突入</a>"
      }
     ]
    },
    {
     "cls": "b",
     "cells": [
      {
       "id": "l",
       "cls": null,
       "html": "1945/04/30　　<a href=\"../1945/04hitle.html\">\nヒトラー自殺</a>"
      }
     ]
    },
    {
     "cls": "b",
     "cells": [
      {
       "id": "l",
       "cls": null,
       "html": "1945/05/07　　<a href=\"../1945/05d_kof.html\">\nドイツ、無条件降伏　（ベルリン陥落）</a>"
      }
     ]
    }
   ]
  },
  {
   "type": "raw",
   "tag": "div",
   "attrs": {
    "class": "hidden"
   },
   "html": "<a name=\"s3\"></a>\n<a href=\"#s3\">＝</a><a href=\"#s2\">△</a><a href=\"#h\">◎</a><a href=\"#s4\">▽</a><a href=\"#s3\">＝</a>"
  },
  {
   "type": "raw",
   "tag": "div",
   "attrs": {
    "class": "tx"
   },
   "html": "\n<div>ヒムラーは、一九四三年には<a href=\"../p/hitler_a.html\">ヒトラー</a>につぐ第三帝国第二番目の人物にのしあがった。\n彼は良家の出身であり、順調に大学を卒業していたので、単純で人のよい家父長的な性格があり、\n部下には自由に腕をふるわせていた。\nしたがって親衛隊の内部では、おたがいに親密な信頼関係があり、団結がかたく、ヒムラーは部下から無条件に信頼されていた。</div>\n<div>ドイツ支配勢力の大半にとっては帝国主義政策のための一手段にすぎなかった狂気じみたナチスの諸政策を、\nヒムラーたちは疑うことも知らずにまじめに信じこんで実行したのであって、ここに彼らの悲劇があったのである。\n巨大な犯罪組織の大親分といった印象が彼にはまったくなくて、\n「まるで田舎の小学校長のようだ」といわれてきたのもこのゆえである。</div>\n<div class=\"r\"><span class=\"f9\"><a href=\"../text/mo_sek15.html\">村瀬興雄 「世界の歴史（15）」</a>\n　Ｐ．３６０</span></div>\n"
  },
  {
   "type": "raw",
   "tag": "div",
   "attrs": {
    "class": "hidden"
   },
   "html": "<a name=\"s4\"></a>\n<a href=\"#s4\">＝</a><a href=\"#s3\">△</a><a href=\"#h\">◎</a><a href=\"#s5\">▽</a><a href=\"#s4\">＝</a>"
  },
  {
   "type": "raw",
   "tag": "div",
   "attrs": {
    "class": "tx"
   },
   "html": "\n<div>ハインリヒ・ヒムラー。その父は高等学校の校長をつとめたこともあり、ヒムラー自身、一見すると、\n物腰のやわらかい学校の校長のようなタイプにみえた。\nだが実際には、そうした外見とはうらはらに、彼は<a href=\"../p/hitler_a.html\">ヒトラー</a>の人種理論の忠実な使徒として、過酷なナチスの弾圧政治の実行者となったのだった。\nあの悪名たかい秘密国家警察もふくめて、すべての政治警察機構は親衛隊の組織に組みいれられ、\nヒムラーとその協力者ハイドリヒの意のままに動かされた。</div>\n<div class=\"r\"><span class=\"f9\"><a href=\"../text/nn1hitle.html\">野田宣雄 「ヒトラーの時代（上）」</a>\n　Ｐ．６６</span></div>\n"
  },
  {
   "type": "raw",
   "tag": "div",
   "attrs": {
    "class": "off"
   },
   "html": "<a name=\"s5\"></a>\n<a href=\"#s5\">＝</a><a href=\"#s4\">△</a><a href=\"#h\">◎</a><a href=\"#s5\">▽</a><a href=\"#s5\">＝</a>"
  },
  {
   "type": "raw",
   "tag": "div",
   "attrs": {
    "class": "off"
   },
   "html": "<span class=\"m_g\">エピソード</span>\n調査中。"
  },
  {
   "type": "cyu",
   "html": "※　「クリック２０世紀」では、引用部分を除いて、固有名詞などの表記を極力統一するよう努めています。\n<br>「ハインリッヒ・ヒムラー」は「ハインリヒ・ヒムラー」とも表記されることがあります。\n"
  },
  {
   "type": "taro",
   "html": "<a href=\"http://www.c20.jp/\">http://www.c20.jp/</a><br><a href=\"mailto:uh@usleaf2001.com\">お便り ドシドシ</a>"
  },
  {
   "type": "fnavi",
   "html": "\n<a href=\"../index.html\">クリック２０世紀 トップ</a>\n ＞ <a href=\"06h.html\">人物ファイル一覧　（ハ）</a>\n ＞ <a href=\"#h\">ハインリッヒ・ヒムラー</a>\n　　<span class=\"fmark\"><a href=\"#h\">□◎□</a></span>"
  }
 ]
}