{
 "path": "p/htadasu.html",
 "type": "person",
 "title": "林 董　／ クリック ２０世紀",
 "description": "●世界と日本の近現代史を年表に再現。人物紹介も充実。●年表の2000を超える項目は史実へのインデックスでもある。●歴史は足跡。見つめると人間が、ドラマが、そして未来が見えてくる。  ・・・ Good luck !",
 "css": [
  "../all.css",
  "p.css"
 ],
 "baseClass": "base",
 "blocks": [
  {
   "type": "edit_bar",
   "kind": "e_bar",
   "html": "<a name=\"h\"></a>"
  },
  {
   "type": "navi",
   "html": "\n<a href=\"../index.html\">目次</a> ＞ 年表 ＞ 事項 ＞ 詳細　／　<span class=\"now\">他</span>　　　<a href=\"javascript:history.back()\"><b>&lt;&lt;&lt;&lt;</b></a>"
  },
  {
   "type": "title",
   "html": "林 董"
  },
  {
   "type": "title2",
   "html": "1850 － 1913"
  },
  {
   "type": "raw",
   "tag": "div",
   "attrs": {
    "class": "name"
   },
   "html": "\n[ はやし・ただす ]"
  },
  {
   "type": "raw",
   "tag": "div",
   "attrs": {
    "class": "prof"
   },
   "html": "\n外相、逓相、外務次官、駐英公使"
  },
  {
   "type": "raw",
   "tag": "table",
   "attrs": {
    "class": "off"
   },
   "html": "<tbody><tr><td class=\"lt\"><a href.html\"=\"\">　</a></td><td class=\"lt\"><a href.html\"=\"\">　</a></td><td class=\"lt\"><a href.html\"=\"\">　</a></td><td class=\"lt\"><a href.html\"=\"\">　</a></td></tr></tbody>"
  },
  {
   "type": "raw",
   "tag": "div",
   "attrs": {
    "class": "off"
   },
   "html": "<span class=\"m_r\">エピソード 1</span>調査中。"
  },
  {
   "type": "raw",
   "tag": "div",
   "attrs": {
    "class": "hidden"
   },
   "html": "<a name=\"s1\"></a>\n<a href=\"#s1\">＝</a><a href=\"#h\">△</a><a href=\"#h\">◎</a><a href=\"#s2\">▽</a><a href=\"#s1\">＝</a>"
  },
  {
   "type": "timeline",
   "rows": [
    {
     "cls": "",
     "cells": [
      {
       "id": null,
       "cls": "hist",
       "html": "\n・　千葉県出身。蘭医で順天堂創立者の五男に生まれ、幕府御殿医の養子となる。"
      }
     ]
    },
    {
     "cls": "",
     "cells": [
      {
       "id": null,
       "cls": "hist",
       "html": "\n・　ヘボンらに英語を習い、幕府留学生としてイギリスに学ぶ。"
      }
     ]
    },
    {
     "cls": "",
     "cells": [
      {
       "id": null,
       "cls": "hist",
       "html": "\n・　帰国後、箱館戦争に参加。のち明治政府に出仕。岩倉使節に随行。"
      }
     ]
    },
    {
     "cls": "",
     "cells": [
      {
       "id": null,
       "cls": "hist",
       "html": "\n・　香川県知事などを歴任後、外務次官となり、条約改正、日清戦時外交に活躍。"
      }
     ]
    },
    {
     "cls": "",
     "cells": [
      {
       "id": null,
       "cls": "hist",
       "html": "\n・　その後、駐露公使を経て駐英公使となり、<a href=\"../1902/01je_do.html\"></a><a href=\"../1902/01je_do.html\">日英同盟</a>の締結に成功。"
      }
     ]
    },
    {
     "cls": "",
     "cells": [
      {
       "id": null,
       "cls": "hist",
       "html": "\n・　<a href=\"../1906/saio1_1.html\">西園寺内閣①</a>で外相に就任、日韓協約③を締結。<a href=\"../1911/saio2_1.html\">西園寺内閣②</a>では逓相となる。"
      }
     ]
    }
   ]
  },
  {
   "type": "raw",
   "tag": "div",
   "attrs": {
    "class": "hidden"
   },
   "html": "<a name=\"s2\"></a>\n<a href=\"#s2\">＝</a><a href=\"#s1\">△</a><a href=\"#h\">◎</a><a href=\"#s3\">▽</a><a href=\"#s2\">＝</a>"
  },
  {
   "type": "timeline",
   "rows": [
    {
     "cls": "n",
     "cells": [
      {
       "id": "l",
       "cls": null,
       "html": "1901/10/16　　<a href=\"../1901/10je_do.html\">\n日英同盟交渉開始</a>"
      }
     ]
    },
    {
     "cls": "b",
     "cells": [
      {
       "id": "l",
       "cls": null,
       "html": "1902/01/30　　<a href=\"../1902/01je_do.html\">\n日英同盟①調印</a>"
      }
     ]
    },
    {
     "cls": "n",
     "cells": [
      {
       "id": "l",
       "cls": null,
       "html": "1903/12/31　　<a href=\"../1903/12enjyo.html\">\n小村外相、林駐英公使に対英財政援助要請を訓令</a>　（04/01/02 拒否）"
      }
     ]
    },
    {
     "cls": "b",
     "cells": [
      {
       "id": "l",
       "cls": null,
       "html": "1904/02/10　　<a href=\"../1904/02jr_wa.html\">\n対露宣戦布告</a>　（<a href=\"../them/jr_war.html\">日露戦争</a>勃発）"
      }
     ]
    },
    {
     "cls": "b",
     "cells": [
      {
       "id": "l",
       "cls": null,
       "html": "1905/05/27　　<a href=\"../1905/05nihon.html\">\n日本海海戦</a>　（～05/28／連合艦隊司令長官：<a href=\"../p/theihaci.html\">東郷平八郎</a>）"
      }
     ]
    },
    {
     "cls": "n",
     "cells": [
      {
       "id": "l",
       "cls": null,
       "html": "1905/08/12　　<a href=\"../1905/08je_d2.html\">\n日英同盟②調印</a>"
      }
     ]
    },
    {
     "cls": "b",
     "cells": [
      {
       "id": "l",
       "cls": null,
       "html": "1905/09/05　　<a href=\"../1905/09portm.html\">\nポーツマス条約調印</a>　（首席全権：<a href=\"../p/kjutaro.html\">小村寿太郎</a>／<a href=\"../them/jr_war.html\">日露戦争</a>終結）"
      }
     ]
    },
    {
     "cls": "g",
     "cells": [
      {
       "id": "l",
       "cls": null,
       "html": "1906/01/07　　<a href=\"../1906/saio1_1.html\">\n西園寺内閣①成立</a>　（首相：<a href=\"../p/skinmoci.html\">西園寺公望</a>）"
      }
     ]
    },
    {
     "cls": "n",
     "cells": [
      {
       "id": "l",
       "cls": null,
       "html": "1906/03/03　　<a href=\"../1906/03katob.html\">\n加藤外相辞任</a>　（鉄道国有化に反対して）"
      }
     ]
    },
    {
     "cls": "n",
     "cells": [
      {
       "id": "l",
       "cls": null,
       "html": "1907/07/03　　<a href=\"../1907/07missi.html\">\n伊藤統監、韓国皇帝にハーグ密使事件を追及</a>"
      }
     ]
    },
    {
     "cls": "n",
     "cells": [
      {
       "id": "l",
       "cls": null,
       "html": "1907/07/19　　<a href=\"../1907/07joisy.html\">\n韓国皇帝、譲位の詔勅を発表</a>"
      }
     ]
    },
    {
     "cls": "b",
     "cells": [
      {
       "id": "l",
       "cls": null,
       "html": "1907/07/24　　<a href=\"../1907/07jk_k3.html\">\n日韓協約③調印</a>"
      }
     ]
    },
    {
     "cls": "b",
     "cells": [
      {
       "id": "l",
       "cls": null,
       "html": "1907/07/30　　<a href=\"../1907/07jr_k1.html\">\n日露協約①調印</a>"
      }
     ]
    },
    {
     "cls": "n",
     "cells": [
      {
       "id": "l",
       "cls": null,
       "html": "1907/08/01　　<a href=\"../1907/08gunka.html\">\n韓国軍解散式</a>"
      }
     ]
    },
    {
     "cls": "n",
     "cells": [
      {
       "id": "l",
       "cls": null,
       "html": "1908/07/04　　<a href=\"../1908/saio1_9.html\">\n西園寺内閣①総辞職</a>"
      }
     ]
    },
    {
     "cls": "g",
     "cells": [
      {
       "id": "l",
       "cls": null,
       "html": "1911/08/30　　<a href=\"../1911/saio2_1.html\">\n西園寺内閣②成立</a>　（首相：<a href=\"../p/skinmoci.html\">西園寺公望</a>）"
      }
     ]
    },
    {
     "cls": "b",
     "cells": [
      {
       "id": "l",
       "cls": null,
       "html": "1912/07/29　　<a href=\"../1912/07mhogy.html\">\n明治天皇崩御</a>"
      }
     ]
    },
    {
     "cls": "n",
     "cells": [
      {
       "id": "l",
       "cls": null,
       "html": "1912/12/05　　<a href=\"../1912/saio2_9.html\">\n西園寺内閣②総辞職</a>"
      }
     ]
    }
   ]
  },
  {
   "type": "raw",
   "tag": "div",
   "attrs": {
    "class": "hidden"
   },
   "html": "<a name=\"s3\"></a>\n<a href=\"#s3\">＝</a><a href=\"#s2\">△</a><a href=\"#h\">◎</a><a href=\"#s4\">▽</a><a href=\"#s3\">＝</a>"
  },
  {
   "type": "raw",
   "tag": "div",
   "attrs": {
    "class": "tx"
   },
   "html": "\n<div>林董というのは、【中略】　旧幕臣系である。</div>\n<div>幕臣林洞海の養子で、旧幕時代の少年期、横浜で英語をまなんだ。\nかれがのちに外務省きっての会話達者で英文上手の評を得るにいたるもとは、このころにあるらしい。\n慶応二年、幕府が留学生を英国にやることをきめたとき、菊池大麓、中村敬宇らとともにえらばれた。\n齢十六である。</div>\n<div>幕府が瓦解し、帰国を命ぜられ、横浜まで帰ったとき、おりから旧幕府の海将榎本武揚が旧幕艦隊をひきいて品川沖に錨をおろしていた。\n林はこれに投じて函館までゆき、五稜郭にこもったという男だけに、当時のことばでいう血性男児であったのであろう。</div>\n<div>【中略】</div>\n<div>結局、事やぶれて榎本らとともに降伏し、林は他の五百余人とともに津軽藩にあずけられ、青森の寺院で拘留生活をおくった。</div>\n<div>ときの官軍参謀は薩摩の<a href=\"../p/kkiyotak.html\">黒田清隆</a>であったが<a href=\"../p/kkiyotak.html\">黒田</a>は、拘留賊徒のなかの林という人物が英国人と同等程度に英語ができるということを知り、\nひそかに林をよび、かれだけを抜いて東京の新政府でつかおうとした。</div>\n<div>林は返答して、</div>\n<div>「みなと一緒に釈放されるならいいが、自分だけならお断りする」</div>\n<div>といって、ことわった。\nこのことが、のち薩摩系の要人のあいだでの林董観をつくらせ、かれの生涯の信用のもとになったらしい。\n林董は、外交官になったあとでも、薩摩閥からの庇護を多くうけ、仕事がしやすかった。</div>\n<div>明治二十四年外務次官、同三十年駐露公使、同三十三年駐英公使に転じた。\nこの履歴でもわかるように、日清、日露というそれぞれの戦争がはじまる前、\n外交段階における最大の働き手のひとりだった。</div>\n<div class=\"r\"><span class=\"f9\"><a href=\"../text/sr3sakan.html\">司馬遼太郎 「坂の上の雲（３）」</a>\n　Ｐ．７６</span></div>\n"
  },
  {
   "type": "raw",
   "tag": "div",
   "attrs": {
    "class": "hidden"
   },
   "html": "<a name=\"s4\"></a>\n<a href=\"#s4\">＝</a><a href=\"#s3\">△</a><a href=\"#h\">◎</a><a href=\"#s5\">▽</a><a href=\"#s4\">＝</a>"
  },
  {
   "type": "raw",
   "tag": "div",
   "attrs": {
    "class": "off"
   },
   "html": "<span class=\"m_y\">エピソード</span>\n調査中。"
  },
  {
   "type": "raw",
   "tag": "div",
   "attrs": {
    "class": "off"
   },
   "html": "<a name=\"s5\"></a>\n<a href=\"#s5\">＝</a><a href=\"#s4\">△</a><a href=\"#h\">◎</a><a href=\"#s5\">▽</a><a href=\"#s5\">＝</a>"
  },
  {
   "type": "raw",
   "tag": "div",
   "attrs": {
    "class": "off"
   },
   "html": "<span class=\"m_g\">エピソード</span>\n調査中。"
  },
  {
   "type": "cyu",
   "html": "※　「クリック２０世紀」では、引用部分を除いて、固有名詞などの表記を極力統一するよう努めています。\n"
  },
  {
   "type": "taro",
   "html": "<a href=\"http://www.c20.jp/\">http://www.c20.jp/</a><br><a href=\"mailto:uh@usleaf2001.com\">お便り ドシドシ</a>"
  },
  {
   "type": "fnavi",
   "html": "\n<a href=\"../index.html\">クリック２０世紀 トップ</a>\n ＞ <a href=\"06h.html\">人物ファイル一覧　（ハ）</a>\n ＞ <a href=\"#h\">林 董</a>\n　　<span class=\"fmark\"><a href=\"#h\">□◎□</a></span>"
  }
 ]
}