{
 "path": "1928/06ciani.html",
 "type": "article",
 "title": "治安維持法改正①　／ クリック ２０世紀",
 "description": "●世界と日本の近現代史を年表に再現。人物紹介も充実。●年表の2000を超える項目は史実へのインデックスでもある。●歴史は足跡。見つめると人間が、ドラマが、そして未来が見えてくる。  ・・・ Good luck !",
 "css": [
  "../all.css",
  "../b.css",
  "../include/include.css"
 ],
 "baseClass": "base",
 "blocks": [
  {
   "type": "edit_bar",
   "kind": "e_bar",
   "html": "<a name=\"h\"></a>"
  },
  {
   "type": "raw",
   "tag": "div",
   "attrs": {
    "class": "c20"
   },
   "html": "\n<a href=\"../index.html\">－ クリック２０世紀 －</a>"
  },
  {
   "type": "navi",
   "html": "\n<a href=\"../index.html\">目次</a> ＞ <a href=\"../20c/1928.html\">年表</a> ＞ <span class=\"now\">事項</span> ＞ <a href~.html\"=\"\">詳細</a> ／ <a href=\"../p/01a.html\">人物</a> ／ <a href=\"../text/01a.html\">書籍</a> ／ 他"
  },
  {
   "type": "title",
   "html": "治安維持法改正①"
  },
  {
   "type": "title2",
   "html": "1928/06/29"
  },
  {
   "type": "navi2",
   "html": "\n<a href=\"../20c/1918.html\">１０年前</a> &gt;&gt;&gt; <a href=\"../20c/1927.html\">前年</a> &gt;&gt;&gt; <a href=\"../20c/1928.html\">１９２８</a> &gt;&gt;&gt; <a href=\"../20c/1929.html\">翌年</a> &gt;&gt;&gt; <a href=\"../20c/1938.html\">１０年後</a>"
  },
  {
   "type": "headline",
   "cells": [
    "緊急勅令でいきなり治安維持法が強化され、一般国民までがその対象になった。"
   ]
  },
  {
   "type": "raw",
   "tag": "table",
   "attrs": {
    "class": "lt"
   },
   "html": "<tbody><tr><td class=\"lt\"><a href\".html\"=\"\">　</a></td><td class=\"lt\"><a href.html\"=\"\">　</a></td><td class=\"lt\"><a href.html\"=\"\">　</a></td><td class=\"lt\"><a href.html\"=\"\">　</a></td></tr></tbody>"
  },
  {
   "type": "timeline",
   "rows": [
    {
     "cls": "b",
     "cells": [
      {
       "id": "l",
       "cls": null,
       "html": "1925/04/22　　<a href=\"../1925/04ciani.html\">\n治安維持法公布</a>"
      }
     ]
    },
    {
     "cls": "n",
     "cells": [
      {
       "id": "l",
       "cls": null,
       "html": "1927/07/15　　<a href=\"../1927/0727the.html\">\n２７年テーゼ</a>　（コミンテルン日本問題委員会）"
      }
     ]
    },
    {
     "cls": "n",
     "cells": [
      {
       "id": "l",
       "cls": null,
       "html": "1928/02/01　　<a href=\"../1928/02akaha.html\">\n共産党機関紙「赤旗」創刊</a>"
      }
     ]
    },
    {
     "cls": "n",
     "cells": [
      {
       "id": "l",
       "cls": null,
       "html": "1928/03/15　　<a href=\"../1928/03315ji.html\">\n三・一五事件</a>　（共産党関係者一斉検挙）"
      }
     ]
    },
    {
     "cls": "x",
     "cells": [
      {
       "id": "l",
       "cls": null,
       "html": "1928/06/29　　<a 1928=\"\" href\"..=\"\" 06ciani.html\"=\"\">\n治安維持法改正①</a>"
      }
     ]
    },
    {
     "cls": "n",
     "cells": [
      {
       "id": "l",
       "cls": null,
       "html": "1929/02/08　　<a href=\"../1929/02danat.html\">\n山本宣治、政府の弾圧政策を追及</a>　（衆議院予算委員会）"
      }
     ]
    },
    {
     "cls": "n",
     "cells": [
      {
       "id": "l",
       "cls": null,
       "html": "1929/03/05　　<a href=\"../1929/03ciani.html\">\n衆議院、治安維持法改正緊急勅令を事後承認</a>"
      }
     ]
    },
    {
     "cls": "b",
     "cells": [
      {
       "id": "l",
       "cls": null,
       "html": "1929/03/05　　<a href=\"../1929/03yamas.html\">\n山本宣治（衆議院議員）刺殺事件</a>"
      }
     ]
    },
    {
     "cls": "n",
     "cells": [
      {
       "id": "l",
       "cls": null,
       "html": "1929/04/16　　<a href\"..=\"\" 19.html\"=\"\">\n四・一六事件　（共産党員全国一斉検挙／党組織に壊滅的打撃）</a>"
      }
     ]
    },
    {
     "cls": "b",
     "cells": [
      {
       "id": "l",
       "cls": null,
       "html": "1941/03/10　　<a href\"..=\"\" 19.html\"=\"\">\n治安維持法改正②　（強化）</a>"
      }
     ]
    }
   ]
  },
  {
   "type": "raw",
   "tag": "div",
   "attrs": {
    "class": "pt"
   },
   "html": "\n<div class=\"pt_h\">～　強化された点　～</div>\n<div class=\"c\">「死刑」の導入 ／ 対象の拡大（共産主義者→国民全体）</div>\n"
  },
  {
   "type": "raw",
   "tag": "div",
   "attrs": {
    "class": "tx"
   },
   "html": "\n<span class=\"m_v\">taro's トーク</span>\nお役人様、政治家様のお仕事がそれはそれは大変なことは、taroはよくわかっているつもりでございます。\n日々、私たち善良な国民のため、寝る間も惜しんでやってらっしゃることはよく承知しているつもりでございます。\nただ、ゆっくり休む間もないからでございましょうか、発想が少しおバカなような気がするのでございます。\n治安が心配だからと治安維持法を作り、まだ心配だからとそれを改正強化する、そうしてびしびし取り締まる、\nそれで事足れりとするのはいかがなものでございましょうか。\nすこおし哲学されてはどうかと思うのです。\n社会にひずみが生まれるにはそれなりの理由がございましょう、大きなひずみがうまれるにはこれまた相応の理由がございましょう。\nそれが何なのか、そこを考えずに、取り締まりばかりに励んでも、ザルで水をすくうようなお話。\n先々のことを考えますと、結局何の役にも立たないばかりか、いたずらに時を浪費して、社会の病を手遅れの状態にしてしまうのではないかと、\ntaroはそこが心配なのでございます。\nそれとも、お役人様、政治家様がたは、退官後、引退後のことは知ったこっちゃねえと。まさかそういうことでは。\nそんなこと、あろうはずがございませんわねぇ、おホホホホ。\nどうぞおカゼなどお召しになりませんよう。かしこ。\n"
  },
  {
   "type": "raw",
   "tag": "div",
   "attrs": {
    "class": "tx"
   },
   "html": "\n<div><span class=\"m_b\">引用</span><a href=\"../1927/tanaa_1.html\">田中内閣</a>は<a href=\"../1928/03315ji.html\">三・一五</a>の大量検挙を行なったあと、警察の発表や右翼の活動によって共産主義の恐怖をあおり、\n治安維持法を改悪し、最高刑死刑とする苛酷な法案を用意した。\nしかしこの法案は議会に提出されたが会期が短かくもとより通過の見込みはなかった。\nそのため政府は急いで五月七日議会を閉会し、議会でまったく審議も行なわれなかった改悪案を、\n六月二九日緊急勅令によって公布した。</div>\n<div class=\"txr\"><a href=\"../text/st2yamas.html\">佐々木敏二 「山本宣治（下）」</a>\n　Ｐ．２５２<span class=\"book\"><a href=\"http://www.amazon.co.jp/exec/obidos/redirect?link_code=ur2&amp;tag=click20thcetu-22&amp;camp=247&amp;creative=1211&amp;path=ASIN%2F4938303019%2Fqid%3D1147088125%2Fsr%3D1-5%2Fref%3Dsr_1_8_5\" target=\"_blank\">この本を入手</a><img src=\"http://www.assoc-amazon.jp/e/ir?t=click20thcetu-22&amp;l=ur2&amp;o=9\" width=\"1\" height=\"1\" border=\"0\" alt=\"\" style=\"border:none !important; margin:0px !important;\"></span></div>\n"
  },
  {
   "type": "raw",
   "tag": "div",
   "attrs": {
    "class": "tx"
   },
   "html": "\n<div><span class=\"m_b\">引用</span>六月二九日、勅令第一二九号「治安維持法中改正緊急勅令」が公布された。\nこれは四月二七日政府より第五五議会に提出され、審議未了となったものとほとんど同一のものであった。\nその要点は第一条の改悪であり、</div>\n<div>第一条　国体ヲ変革スルコトヲ目的トシテ結社ヲ組織シタル者又結社ノ役員其ノ他指導者タル任務ニ従事シタル者ハ\n死刑又ハ無期若クハ五年以上ノ懲役又ハ禁錮ニ処シ情ヲ知リテ結社ニ加入シタル者又ハ結社ノ目的遂行ノ為ニスル行為ヲ為シタル者ハ\n二年以上ノ有期ノ懲役又ハ禁錮ニ処ス</div>\n<div>私有財産制度ヲ否認スルコトヲ目的トシテ結社ヲ組織シタル者結社ニ加入シタル者又ハ結社ノ目的遂行ノ為ニスル行為ヲ為シタル者ハ\n十年以下ノ懲役又ハ禁錮ニ処ス</div>\n<div>というものである。\n緊急勅令は「公共ノ安全ヲ保持シ又ハ其ノ災厄ヲ避クル為緊急ノ必要ニ由リ」（大日本帝国憲法第八条）という要件を必要とする。\n第五五議会に政府が提案したとき、政友会内部にも反対があり、まして野党や無産政党、学者はこぞって反対の声をあげていた。\n政府が議会での成立をさけた法案に二ヵ月もたたないうちに「緊急の必要」が生じたとは誰にも考えられなかった。\nその審議にあたった枢密院では、久保田譲、江木千之、松室致などが強硬に反対し、政府に再考をせまり、\n年末の通常議会での議案とするようにとせまった。\nしかし枢密院の委員会では五対三、枢密院御前会議では一二対五で承認された。\n<a href=\"../1926/waka1_1.html\">若槻内閣</a>が要請した財政危機救済の緊急勅令を拒否した枢密院が、さほどの緊急性もない治安維持法改悪案を承認した。\nしかしさすがに枢密院も、あまりに肩入れしている姿勢なのを感じたのか、\n緊急勅令の濫用に警告を発し、社会政策による国民生活の安定に努力するようにとの条件をつけざるをえなかった。</div>\n<div>しかし事情はどうあれ、緊急勅令によって死刑法・治安維持法が即日施行されることになった。\nこれが社会民衆党、日本労働党をより一層右傾化させ、右翼団体の活動をより活発にさせ、\n新党準備会の活動をより困難にさせて行くのである。</div>\n<div class=\"txr\"><a href=\"../text/st2yamas.html\">佐々木敏二 「山本宣治（下）」</a>\n　Ｐ．２５６<span class=\"book\"><a href=\"http://www.amazon.co.jp/exec/obidos/redirect?link_code=ur2&amp;tag=click20thcetu-22&amp;camp=247&amp;creative=1211&amp;path=ASIN%2F4938303019%2Fqid%3D1147088125%2Fsr%3D1-5%2Fref%3Dsr_1_8_5\" target=\"_blank\">この本を入手</a><img src=\"http://www.assoc-amazon.jp/e/ir?t=click20thcetu-22&amp;l=ur2&amp;o=9\" width=\"1\" height=\"1\" border=\"0\" alt=\"\" style=\"border:none !important; margin:0px !important;\"></span></div>\n"
  },
  {
   "type": "cyu",
   "html": "※　「クリック２０世紀」では、引用部分を除いて、固有名詞などの表記を極力統一するよう努めています。\n"
  },
  {
   "type": "taro",
   "html": "<a href=\"http://www.c20.jp/\">http://www.c20.jp/</a><br><a href=\"mailto:taro@c20.jp\">おたよりはこちら</a>"
  },
  {
   "type": "raw",
   "tag": "div",
   "attrs": {},
   "html": "\n<script type=\"text/javascript\"><!--\ngoogle_ad_client = \"pub-3232598861909913\";\n/* 468x15, 作成済み 08/10/23 */\ngoogle_ad_slot = \"9077774385\";\ngoogle_ad_width = 468;\ngoogle_ad_height = 15;\n//-->\n</script>\n<script type=\"text/javascript\" src=\"http://pagead2.googlesyndication.com/pagead/show_ads.js\">\n</script>\n"
  },
  {
   "type": "fnavi",
   "html": "\n<a href=\"../index.html\">クリック２０世紀 トップ</a>\n ＞ <a href=\"../20c/1928.html\">１９２８年</a>\n ＞ <a href=\"#h\">治安維持法改正①</a>\n　　<span class=\"fmark\"><a href=\"#h\">□◎□</a></span>"
  }
 ]
}